diatomic/__init__.py
diatomic/calculate.py
diatomic/operators.py
diatomic/plotting.py
diatomic/systems.py
diatomic_py-2.0.2.dist-info/licenses/LICENSE
diatomic_py-2.0.2.dist-info/METADATA
diatomic_py-2.0.2.dist-info/WHEEL
diatomic_py-2.0.2.dist-info/top_level.txt
diatomic_py-2.0.2.dist-info/RECORD
