Metadata-Version: 2.4
Name: diatomic-py
Version: 2.0.2
Summary: A package for calculating rotational and hyperfine structure of singlet diatomic molecules.
Author-email: Jake Blackmore <j.a.blackmore@durham.ac.uk>, Tom Hepworth <tom.hepworth@durham.ac.uk>
License: Copyright (c) 2021, Jacob A Blackmore
Keywords: quantum,singlet,diatomic,molecules,hyperfine,hamiltonian
Classifier: Programming Language :: Python :: 3
Classifier: License :: OSI Approved :: BSD License
Classifier: Operating System :: OS Independent
Requires-Python: >=3.10
License-File: LICENSE
Requires-Dist: numpy
Requires-Dist: sympy
Requires-Dist: scipy
Provides-Extra: test
Requires-Dist: pytest; extra == "test"
Provides-Extra: plotting
Requires-Dist: matplotlib; extra == "plotting"
Provides-Extra: docs
Requires-Dist: sphinx; extra == "docs"
Requires-Dist: sphinx-book-theme; extra == "docs"
Provides-Extra: dev
Requires-Dist: diatomic-py[test]; extra == "dev"
Requires-Dist: diatomic-py[docs]; extra == "dev"
Requires-Dist: black; extra == "dev"
Requires-Dist: pre-commit; extra == "dev"
Requires-Dist: ruff; extra == "dev"
Dynamic: license-file
